Workbook
Name Aporte: 'APP CONTROLE FINANCEIRO'!$D$16
Name dividendo_mesal: 'APP CONTROLE FINANCEIRO'!$D$20
Name patrimonio: 'APP CONTROLE FINANCEIRO'!$D$19
Name quantidade_anos: 'APP CONTROLE FINANCEIRO'!$D$17
Name rendimento_carteira: 'APP CONTROLE FINANCEIRO'!$D$12
Name salario: 'APP CONTROLE FINANCEIRO'!$D$11
Name sugestao_investimento: 'APP CONTROLE FINANCEIRO'!$D$13
Name taxa_mensal: 'APP CONTROLE FINANCEIRO'!$D$18

Sheet APP CONTROLE FINANCEIRO
B10: CONFIGURAÇÕES
B11: Salário | D11: 5000
B12: Rendimento Carteira | D12: 0.006
B13: Sugestão de investimento | D13: =D11*30% -> 1500
A15: 2 | B15: INVESTIMENTO MENSAL
A16: 5 | B16: Quanto investir? | D16: 1260
A17: 10 | B17: Por quantos anos? | D17: 10
A18: 20 | B18: Taxa de rendimento? | D18: 0.01079
A19: 30 | B19: Patrimônio acumulado? | D19: =FV(taxa_mensal,quantidade_anos*12,Aporte*-1) -> 306538.11
B20: Dividendos mensais? | D20: =D19*$D$12 -> 1839.2286
B22: CENÁRIOS | D22: Dividendo
B23: Quanto em 2 anos? | C23: =FV($D$18,$A15*12,$D$16*-1) -> 34306.81 | D23: =C23*rendimento_carteira -> 205.84086
B24: Quanto em 5 anos? | C24: =FV($D$18,$A16*12,$D$16*-1) -> 105558.91 | D24: =C24*rendimento_carteira -> 633.35347
B25: Quanto em 10 anos? | C25: =FV($D$18,$A17*12,$D$16*-1) -> 306538.11 | D25: =C25*rendimento_carteira -> 1839.2286
B26: Quanto em 20 anos? | C26: =FV($D$18,$A18*12,$D$16*-1) -> 1417750 | D26: =C26*rendimento_carteira -> 8506.4999
B27: Quanto em 30 anos? | C27: =FV($D$18,$A19*12,$D$16*-1) -> 5445933.8 | D27: =C27*rendimento_carteira -> 32675.603
B31: PERFIL | C31: Conservador
B32: VALOR A SER INVESTIDO POR MÊS | C32: =Aporte -> 1260
B34: TIPO DE FII | C34: Percentual sugerido | D34: Valores
B35: PAPEL | C35: =VLOOKUP($C$31&"-"&B35,'PLANILHA APOIO'!$A:$D,4,FALSE) -> 0.3 | D35: =C35*$C$32 -> 378
B36: TIJOLO | C36: =VLOOKUP($C$31&"-"&B36,'PLANILHA APOIO'!$A:$D,4,FALSE) -> 0.5 | D36: =C36*$C$32 -> 630
B37: HÍBRIDO | C37: =VLOOKUP($C$31&"-"&B37,'PLANILHA APOIO'!$A:$D,4,FALSE) -> 0.1 | D37: =C37*$C$32 -> 126
B38: FOFs | C38: =VLOOKUP($C$31&"-"&B38,'PLANILHA APOIO'!$A:$D,4,FALSE) -> 0.1 | D38: =C38*$C$32 -> 126
B39: DESENVOLVIMENTO | C39: =VLOOKUP($C$31&"-"&B39,'PLANILHA APOIO'!$A:$D,4,FALSE) -> 0 | D39: =C39*$C$32 -> 0
B40: HOTELARIAS | C40: =VLOOKUP($C$31&"-"&B40,'PLANILHA APOIO'!$A:$D,4,FALSE) -> 0 | D40: =C40*$C$32 -> 0
D41: =SUM(D35:D40) -> 1260

Sheet PLANILHA APOIO
A2: CHAVE | B2: PERFIL | C2: TIPO DE FII | D2: % | H2: %
A3: =B3&"-"&C3 -> Conservador-PAPEL | B3: Conservador | C3: PAPEL | D3: 0.3 | G3: Moderado-TIJOLO | H3: =VLOOKUP(G3,$A:$D,4,FALSE) -> 0.35
A4: =B4&"-"&C4 -> Conservador-TIJOLO | B4: Conservador | C4: TIJOLO | D4: 0.5
A5: =B5&"-"&C5 -> Conservador-HÍBRIDO | B5: Conservador | C5: HÍBRIDO | D5: 0.1
A6: =B6&"-"&C6 -> Conservador-FOFs | B6: Conservador | C6: FOFs | D6: 0.1
A7: =B7&"-"&C7 -> Conservador-DESENVOLVIMENTO | B7: Conservador | C7: DESENVOLVIMENTO | D7: 0
A8: =B8&"-"&C8 -> Conservador-HOTELARIAS | B8: Conservador | C8: HOTELARIAS | D8: 0
A9: =B9&"-"&C9 -> Moderado-PAPEL | B9: Moderado | C9: PAPEL | D9: 0.32
A10: =B10&"-"&C10 -> Moderado-TIJOLO | B10: Moderado | C10: TIJOLO | D10: 0.35
A11: =B11&"-"&C11 -> Moderado-HÍBRIDO | B11: Moderado | C11: HÍBRIDO | D11: 0.08
A12: =B12&"-"&C12 -> Moderado-FOFs | B12: Moderado | C12: FOFs | D12: 0.05
A13: =B13&"-"&C13 -> Moderado-DESENVOLVIMENTO | B13: Moderado | C13: DESENVOLVIMENTO | D13: 0.1
A14: =B14&"-"&C14 -> Moderado-HOTELARIAS | B14: Moderado | C14: HOTELARIAS | D14: 0.1
A15: =B15&"-"&C15 -> Agressivo-PAPEL | B15: Agressivo | C15: PAPEL | D15: 0.5
... A20: =B20&"-"&C20 -> Agressivo-HOTELARIAS | B20: Agressivo | C20: HOTELARIAS | D20: 0.1
